{"version": "1", "message": "ERROR: Hidden Testcases server unreachable.", "problem_id": "ADS-1 remedial-4", "user_id": "Arepallyrakesh", "score": {"sample": {"0": {"execution_time": 0.18224310874938965, "passed": false}, "1": {"execution_time": 0.15626811981201172, "passed": false}, "2": {"execution_time": 0.1718912124633789, "passed": false}, "3": {"execution_time": 0.1562197208404541, "passed": false}, "4": {"execution_time": 0.15628600120544434, "passed": false}, "5": {"execution_time": 0.17198777198791504, "passed": false}, "6": {"execution_time": 0.1719067096710205, "passed": false}}}, "check_style_score": "0/1"}